features/__init__.py
features/main.py
lusidtools/__init__.py
lusidtools/apps/__init__.py
lusidtools/apps/flush_transactions.py
lusidtools/apps/upsert_holdings.py
lusidtools/apps/upsert_instruments.py
lusidtools/apps/upsert_portfolios.py
lusidtools/apps/upsert_quotes.py
lusidtools/apps/upsert_transactions.py
lusidtools/cocoon/__init__.py
lusidtools/cocoon/async_tools.py
lusidtools/cocoon/cocoon.py
lusidtools/cocoon/cocoon_printer.py
lusidtools/cocoon/dateorcutlabel.py
lusidtools/cocoon/instruments.py
lusidtools/cocoon/properties.py
lusidtools/cocoon/seed_sample_data.py
lusidtools/cocoon/systemConfiguration.py
lusidtools/cocoon/transaction_type_upload.py
lusidtools/cocoon/utilities.py
lusidtools/cocoon/validator.py
lusidtools/cocoon/config/domain_settings.json
lusidtools/cocoon/config/seed_sample_data.json
lusidtools/commands/__init__.py
lusidtools/commands/agg.py
lusidtools/commands/commands.py
lusidtools/commands/cons.py
lusidtools/commands/delete_portfolio_properties.py
lusidtools/commands/hld.py
lusidtools/commands/instr_id.py
lusidtools/commands/port_props_set.py
lusidtools/commands/portfolios.py
lusidtools/commands/quotes.py
lusidtools/commands/rec.py
lusidtools/commands/scopes.py
lusidtools/commands/targets.py
lusidtools/commands/txn.py
lusidtools/commands/txn_config.py
lusidtools/extract/__init__.py
lusidtools/extract/group_holdings.py
lusidtools/iam/__init__.py
lusidtools/iam/roles.py
lusidtools/jupyter_tools/__init__.py
lusidtools/jupyter_tools/hide_code_button.py
lusidtools/jupyter_tools/stop_execution.py
lusidtools/logger/LusidLogger.py
lusidtools/logger/__init__.py
lusidtools/lpt/__init__.py
lusidtools/lpt/back_compat.py
lusidtools/lpt/cash_ladder.py
lusidtools/lpt/connect_lusid.py
lusidtools/lpt/connect_none.py
lusidtools/lpt/connect_token.py
lusidtools/lpt/create_group_portfolios.py
lusidtools/lpt/create_instr.py
lusidtools/lpt/create_orders.py
lusidtools/lpt/create_portfolios.py
lusidtools/lpt/create_properties.py
lusidtools/lpt/dfq.py
lusidtools-1.0.18.dist-info/LICENSE
lusidtools-1.0.18.dist-info/METADATA
lusidtools-1.0.18.dist-info/WHEEL
lusidtools-1.0.18.dist-info/entry_points.txt
lusidtools-1.0.18.dist-info/top_level.txt
lusidtools-1.0.18.dist-info/RECORD
