Metadata-Version: 2.1
Name: lusidtools
Version: 1.0.18
Summary: Python Tools for LUSID
Home-page: https://github.com/finbourne/lusid-python-tools
Author: FINBOURNE Technology
Author-email: engineering@finbourne.com
License: MIT
Keywords: FINBOURNE,LUSID,LUSID API,python
Requires-Python: >=3.7
License-File: LICENSE
Requires-Dist: urllib3>=1.26.9
Requires-Dist: requests>=2.27.1
Requires-Dist: coloredlogs>=14.0
Requires-Dist: detect_delimiter>=0.1
Requires-Dist: flatten-json>=0.1.7
Requires-Dist: pandas>=1.1.4
Requires-Dist: PyYAML>=5.4
Requires-Dist: tqdm>=4.52.0
Requires-Dist: openpyxl>=3.0.7
Requires-Dist: xlrd~=1.2
Requires-Dist: pytz>=2019.3
Requires-Dist: IPython>=7.31.1
Requires-Dist: lusid-sdk-preview<2,>=0.11.4425
